oilmm/__init__.py
oilmm/_version.py
oilmm/autograd.py
oilmm/imogp.py
oilmm/jax.py
oilmm/mogp.py
oilmm/oilmm.py
oilmm/tensorflow.py
oilmm/test.py
oilmm/torch.py
oilmm/util.py
tests/__init__.py
tests/test_model.py
tests/test_oilmm.py
tests/util.py
oilmm-0.5.0.dist-info/LICENCE.txt
oilmm-0.5.0.dist-info/METADATA
oilmm-0.5.0.dist-info/WHEEL
oilmm-0.5.0.dist-info/top_level.txt
oilmm-0.5.0.dist-info/RECORD
