Metadata-Version: 2.1
Name: oilmm
Version: 0.5.0
Summary: Implementation of the Instantaneous Orthogonal Linear Mixing Model
Home-page: https://github.com/wesselb/oilmm
Author: Wessel Bruinsma
Author-email: wessel.p.bruinsma@gmail.com
License: MIT
Requires-Python: >=3.6
License-File: LICENCE.txt
Requires-Dist: numpy (>=1.16)
Requires-Dist: stheno (>=1.1.3)
Requires-Dist: varz (>=0.7.1)
Requires-Dist: backends (>=1.4.8)
Requires-Dist: backends-matrix (>=1.1.2)
Requires-Dist: plum-dispatch (>=2)
Requires-Dist: probmods (>=0.3.1)
